Workbook

Sheet READ ME
A1: HRO-COST-SHADOW-V1
A2: HRO Intent Flow Cost-Benefit Explorer — shadow model
A4: HOW TO USE
A5: 1. Edit the YELLOW cells only: Inputs, Flow Classes (containment / sampling overrides), Assumptions (override column),
A6: Model Stack (model choice) and Systems (Integrated? = No for systems the client will not connect).
A7: 2. Results update live via formulas — they give a FAIR, DIRECTIONAL estimate of the annual business case.
A8: 3. Upload this file back into the app (Scenario Builder → Import workbook). The app reads ONLY your inputs and
A9: reprices with the exact engine — per-intent pricing, adoption ramp, fan-out, SME overrides and validation.
A11: IMPORTANT
A12: - The spreadsheet formulas are a simplified per-flow-class approximation exported from the engine at the
A13: configuration current when this file was generated. The app's number is the authoritative one.
A14: - Do not rename sheets, delete key columns (column A) or reorder columns; the importer reads them by position.

Sheet Inputs
A1: Key | B1: Input | C1: Value | D1: Notes
A2: annualTransactions | B2: Annual HR transactions | C2: 50000 | D2: Total yearly transaction volume in scope.
A3: employees | B3: Employees served | C3: 5000 | D3: Headcount served by the HRO scope.
A4: numSystems | B4: HR systems in landscape | C4: 5 | D4: Systems of record the agents must touch.
A5: countries | B5: Countries | C5: 3 | D5: Countries in scope (drives localization & onboarding).
A6: sector | B6: Sector | C6: technology | D6: Client industry (free text).
A7: companyType | B7: Geographic span | C7: multi-country | D7: single-country | multi-country | global
A8: isolationTier | B8: Compute isolation tier | C8: siloed | D8: pooled | siloed | dedicated
A9: hrHourlyCostUsd | B9: As-is HR cost ($/hr) | C9: 45 | D9: Blended hourly cost of today's HR handling.
A10: hitlHourlyCostUsd | B10: To-be HITL cost ($/hr) | C10: 35 | D10: Hourly cost of human reviewers in the to-be model.
A11: adoptionRate | B11: Adoption rate (0-1, scalar) | D11: OPTIONAL scalar fallback. Ignored when the Y1-Y3 ramp below is filled. Blank = engine default ramp.
A12: hitlSamplingRate | B12: HITL sampling rate (0-1) | D12: OPTIONAL scalar fallback. Blank = per-flow-class defaults.
A13: landscapeMaturity | B13: Landscape maturity | D13: OPTIONAL. clean | mixed | legacy. Blank = mixed.
A14: contractYears | B14: Contract length (years) | D14: OPTIONAL. Blank = 3-year default.
A15: reworkRatePct | B15: As-is rework rate (%) | D15: OPTIONAL. Share of transactions needing rework today.
A16: peakLoadFactor | B16: Peak load factor | D16: OPTIONAL. 1.0-1.5 seasonal peak provisioning.
A17: adoptionRampY1 | B17: Adoption ramp Year 1 (0-1) | D17: OPTIONAL. Fill all three or none. Fraction of volume in the automated channel that year. Blank = engine default ramp (40/75/100%).
A18: adoptionRampY2 | B18: Adoption ramp Year 2 (0-1) | D18: OPTIONAL. Fill all three or none. Fraction of volume in the automated channel that year. Blank = engine default ramp (40/75/100%).
A19: adoptionRampY3 | B19: Adoption ramp Year 3 (0-1) | D19: OPTIONAL. Fill all three or none. Fraction of volume in the automated channel that year. Blank = engine default ramp (40/75/100%).

Sheet Ref
A1: tier | B1: mult
A2: pooled | B2: 1
A3: siloed | B3: 1.4
A4: dedicated | B4: 2.5
A5: company | B5: mult
A6: single-country | B6: 1
A7: multi-country | B7: 1.1
A8: global | B8: 1.2
A9: maturity | B9: mult
A10: clean | B10: 0.8
A11: mixed | B11: 1
A12: legacy | B12: 1.4
A13: refTier | B13: 1.4
A14: refLoc | B14: 1.1
A15: refMat | B15: 1
A16: refAdoption | B16: 1

Sheet Flow Classes
A1: Key | B1: Flow class | C1: Share | D1: Txns/yr | E1: Default containment | F1: Containment override | G1: Effective containment | H1: Contained txns | I1: AI $/txn (ref) | J1: Infra $/txn (ref) | K1: Other $/txn (ref) | L1: As-is min | M1: To-be min | N1: Default HITL sampling | O1: Sampling override | P1: Effective sampling | Q1: AI cost | R1: Infra cost | S1: Other cost | T1: Human cost | U1: Build cost | V1: Benefit | W1: Net
A2: fc1-deterministic | B2: Deterministic Self-Service | C2: 0.49724995 | D2: =C2*IF(Inputs!$C$17<>"",AVERAGE(Inputs!$C$17,Inputs!$C$18,Inputs!$C$19),IF(Inputs!$C$11="",0.71667,Inputs!$C$11))*Inputs!$C$2 | E2: 0.95 | G2: =IF(F2="",E2,F2) | H2: =D2*G2 | I2: 0.030518838 | J2: 0.021226648 | K2: 0 | L2: 12.31476 | M2: 0.50326023 | N2: 0.05 | P2: =IF(O2="",IF(Inputs!$C$12="",N2,Inputs!$C$12),O2) | Q2: =D2*I2*(VLOOKUP(Inputs!$C$8,Ref!$A$2:$B$4,2,FALSE)/Ref!$B$13) | R2: =D2*J2*(VLOOKUP(Inputs!$C$8,Ref!$A$2:$B$4,2,FALSE)/Ref!$B$13) | S2: =D2*K2 | T2: =H2*(M2/60)*Inputs!$C$10*P2+(D2-H2)*(L2/60)*Inputs!$C$10 | U2: =D2*0.8986666666666666*(IF(Inputs!$C$13="",Ref!$B$11,VLOOKUP(Inputs!$C$13,Ref!$A$10:$B$12,2,FALSE))/Ref!$B$15) | V2: =H2*MAX(0,L2-M2)/60*Inputs!$C$9+H2*0.35857291049199796 | W2: =V2-Q2-R2-S2-T2-U2
A3: fc2-policy | B3: Grounded Policy Answer | C3: 0.34303467 | D3: =C3*IF(Inputs!$C$17<>"",AVERAGE(Inputs!$C$17,Inputs!$C$18,Inputs!$C$19),IF(Inputs!$C$11="",0.71667,Inputs!$C$11))*Inputs!$C$2 | E3: 0.88 | G3: =IF(F3="",E3,F3) | H3: =D3*G3 | I3: 0.08174621 | J3: 0.01878239 | K3: 0.98994748 | L3: 22.334594 | M3: 3.0205362 | N3: 0.15 | P3: =IF(O3="",IF(Inputs!$C$12="",N3,Inputs!$C$12),O3) | Q3: =D3*I3*(VLOOKUP(Inputs!$C$8,Ref!$A$2:$B$4,2,FALSE)/Ref!$B$13)*(VLOOKUP(Inputs!$C$7,Ref!$A$6:$B$8,2,FALSE)/Ref!$B$14) | R3: =D3*J3*(VLOOKUP(Inputs!$C$8,Ref!$A$2:$B$4,2,FALSE)/Ref!$B$13)*(VLOOKUP(Inputs!$C$7,Ref!$A$6:$B$8,2,FALSE)/Ref!$B$14) | S3: =D3*K3 | T3: =H3*(M3/60)*Inputs!$C$10*P3+(D3-H3)*(L3/60)*Inputs!$C$10 | U3: =D3*1.1266666666666663*(IF(Inputs!$C$13="",Ref!$B$11,VLOOKUP(Inputs!$C$13,Ref!$A$10:$B$12,2,FALSE))/Ref!$B$15) | V3: =H3*MAX(0,L3-M3)/60*Inputs!$C$9+H3*1.9255918113077755 | W3: =V3-Q3-R3-S3-T3-U3
A4: fc3-multiagent | B4: Multi-Agent Transaction | C4: 0.1390944 | D4: =C4*IF(Inputs!$C$17<>"",AVERAGE(Inputs!$C$17,Inputs!$C$18,Inputs!$C$19),IF(Inputs!$C$11="",0.71667,Inputs!$C$11))*Inputs!$C$2 | E4: 0.8 | G4: =IF(F4="",E4,F4) | H4: =D4*G4 | I4: 0.38261813 | J4: 0.035357328 | K4: 0 | L4: 79.547786 | M4: 12.160373 | N4: 0.3 | P4: =IF(O4="",IF(Inputs!$C$12="",N4,Inputs!$C$12),O4) | Q4: =D4*I4*(VLOOKUP(Inputs!$C$8,Ref!$A$2:$B$4,2,FALSE)/Ref!$B$13) | R4: =D4*J4*(VLOOKUP(Inputs!$C$8,Ref!$A$2:$B$4,2,FALSE)/Ref!$B$13) | S4: =D4*K4 | T4: =H4*(M4/60)*Inputs!$C$10*P4+(D4-H4)*(L4/60)*Inputs!$C$10 | U4: =D4*2.326666666666666*(IF(Inputs!$C$13="",Ref!$B$11,VLOOKUP(Inputs!$C$13,Ref!$A$10:$B$12,2,FALSE))/Ref!$B$15) | V4: =H4*MAX(0,L4-M4)/60*Inputs!$C$9+H4*7.284195804195772 | W4: =V4-Q4-R4-S4-T4-U4
A5: fc4-frontier | B5: Frontier Judgment Case | C5: 0.020620988 | D5: =C5*IF(Inputs!$C$17<>"",AVERAGE(Inputs!$C$17,Inputs!$C$18,Inputs!$C$19),IF(Inputs!$C$11="",0.71667,Inputs!$C$11))*Inputs!$C$2 | E5: 0.7 | G5: =IF(F5="",E5,F5) | H5: =D5*G5 | I5: 1.0732363 | J5: 0.047535488 | K5: 0.98994748 | L5: 177.73585 | M5: 41.163522 | N5: 0.6 | P5: =IF(O5="",IF(Inputs!$C$12="",N5,Inputs!$C$12),O5) | Q5: =D5*I5*(VLOOKUP(Inputs!$C$8,Ref!$A$2:$B$4,2,FALSE)/Ref!$B$13)*(VLOOKUP(Inputs!$C$7,Ref!$A$6:$B$8,2,FALSE)/Ref!$B$14) | R5: =D5*J5*(VLOOKUP(Inputs!$C$8,Ref!$A$2:$B$4,2,FALSE)/Ref!$B$13)*(VLOOKUP(Inputs!$C$7,Ref!$A$6:$B$8,2,FALSE)/Ref!$B$14) | S5: =D5*K5 | T5: =H5*(M5/60)*Inputs!$C$10*P5+(D5-H5)*(L5/60)*Inputs!$C$10 | U5: =D5*13.326666666666668*(IF(Inputs!$C$13="",Ref!$B$11,VLOOKUP(Inputs!$C$13,Ref!$A$10:$B$12,2,FALSE))/Ref!$B$15) | V5: =H5*MAX(0,L5-M5)/60*Inputs!$C$9+H5*24.349056603773587 | W5: =V5-Q5-R5-S5-T5-U5

Sheet Assumptions
A1: Key | B1: Assumption | C1: Unit | D1: Default | E1: Override | F1: Rationale
A2: slm-call-cost | B2: Small-model (SLM) call cost | C2: USD per call | D2: 0.002 | F2: Deterministic intake/intent steps run on small models (GPT-4o-mini / Phi class) at roughly $0.15-0.60 per 1M tokens; a routing call consumes ~2-5K tokens.
A3: llm-call-cost | B3: Reasoning-model (LLM) call cost | C3: USD per call | D3: 0.02 | F3: Policy/multi-agent reasoning steps use mid-tier reasoning models (~$2-5 per 1M tokens) with 5-15K tokens of grounded context per call.
A4: frontier-call-cost | B4: Frontier-model call cost | C4: USD per call | D4: 0.12 | F4: Deep-reasoning frontier calls (o-series / Claude-Opus class) with long context and chain-of-thought consume 30-80K tokens.
A5: mcp-action-cost | B5: MCP system action cost | C5: USD per system action | D5: 0.004 | F5: Each Act get/put via the MCP integration layer costs compute, API-management and connector amortization; benchmarked against Azure API Management + Functions consumption pricing.
A6: infra-per-txn | B6: Platform infra per transaction | C6: USD per transaction | D6: 0.015 | F6: Allocated share of AKS, storage, observability, gateway and vector-search infrastructure per completed transaction at pooled-tier utilization.
A7: tier-pooled | B7: Isolation tier multiplier: pooled | C7: multiplier | D7: 1 | F7: Pooled multi-tenant tier is the cost baseline (shared compute, shared model quota).
A8: tier-siloed | B8: Isolation tier multiplier: siloed | C8: multiplier | D8: 1.4 | F8: Siloed tier adds dedicated namespaces, storage and model quotas; ~40% infra/AI uplift per the deck's pricing slide.
A9: tier-dedicated | B9: Isolation tier multiplier: dedicated | C9: multiplier | D9: 2.5 | F9: Dedicated single-tenant deployment forgoes pooling economics entirely; ~2.5x uplift per the deck's pricing slide.
A10: landscape-fanout | B10: Act fan-out per additional system | C10: multiplier per extra system | D10: 0.35 | F10: Each additional system of record beyond the first adds ~35% of the base Act integration effort (not 100% - many intents touch only a subset of the landscape).
A11: country-localization | B11: Localization uplift per additional country | C11: multiplier per extra country | D11: 0.03 | F11: Each additional country adds policy variants, language handling and regulation packs to knowledge-grounded (fc2) and frontier (fc4) flows; +3% AI/infra run cost per extra country, capped at 20 countries.
A12: company-multi-country | B12: Complexity uplift: multi-country | C12: multiplier | D12: 1.1 | F12: Multi-country clients add localization, vendor payroll routing and policy variants to run cost.
A13: company-global | B13: Complexity uplift: global | C13: multiplier | D13: 1.2 | F13: Global clients add time-zone follow-the-sun handling and regulatory breadth.

Sheet Model Stack
A1: Role | B1: Options (key — $/call) | C1: Selected model key | D1: Note
A2: router | B2: gpt-5-mini — $0.002 | gemini-flash — $0.001 | phi-onprem — $0.0008 | D2: Blank = engine default. Model choice reprices AI steps exactly on re-import (spreadsheet totals do not reprice).
A3: reasoning | B3: gpt-5 — $0.02 | claude-sonnet — $0.018 | gemini-pro — $0.014 | D3: Blank = engine default. Model choice reprices AI steps exactly on re-import (spreadsheet totals do not reprice).
A4: frontier | B4: claude-opus — $0.12 | gpt-5-pro — $0.15 | o-series — $0.1 | D4: Blank = engine default. Model choice reprices AI steps exactly on re-import (spreadsheet totals do not reprice).
A5: data | B5: ldm-schema-grounded — $0.02 | nl2sql-slm — $0.006 | frontier-data-agent — $0.06 | D5: Blank = engine default. Model choice reprices AI steps exactly on re-import (spreadsheet totals do not reprice).

Sheet Systems
A1: Key | B1: System | C1: MCP integration | D1: Integrated? | E1: Note
A2: sf-ec | B2: SAP SuccessFactors Employee Central | C2: MCP tool → REST/OData connector | D2: Yes | E2: Set to No if the client will not connect this system: its act-stage actions stay manual (approx. not reflected in spreadsheet totals; exact on re-import).
A3: sf-ecp | B3: SAP SuccessFactors Employee Central Payroll | C3: MCP tool → REST/OData connector | D3: Yes | E3: Set to No if the client will not connect this system: its act-stage actions stay manual (approx. not reflected in spreadsheet totals; exact on re-import).
A4: workday | B4: Workday HCM | C4: MCP tool → REST/OData connector | D4: Yes | E4: Set to No if the client will not connect this system: its act-stage actions stay manual (approx. not reflected in spreadsheet totals; exact on re-import).
A5: benefits-platform | B5: Benefits Administration Platform | C5: MCP tool → API + event webhook | D5: Yes | E5: Set to No if the client will not connect this system: its act-stage actions stay manual (approx. not reflected in spreadsheet totals; exact on re-import).
A6: time-system | B6: Time & Attendance System | C6: MCP tool → REST/OData connector | D6: Yes | E6: Set to No if the client will not connect this system: its act-stage actions stay manual (approx. not reflected in spreadsheet totals; exact on re-import).
A7: ticketing | B7: Case Management / Ticketing | C7: MCP tool → API + event webhook | D7: Yes | E7: Set to No if the client will not connect this system: its act-stage actions stay manual (approx. not reflected in spreadsheet totals; exact on re-import).
A8: knowledge-base | B8: Policy Knowledge Base | C8: MCP tool → RAG retrieval index | D8: Yes | E8: Set to No if the client will not connect this system: its act-stage actions stay manual (approx. not reflected in spreadsheet totals; exact on re-import).
A9: idp | B9: Identity Provider / IAM | C9: MCP tool → OIDC/SCIM | D9: Yes | E9: Set to No if the client will not connect this system: its act-stage actions stay manual (approx. not reflected in spreadsheet totals; exact on re-import).
A10: lms | B10: Learning Management System | C10: MCP tool → REST/OData connector | D10: Yes | E10: Set to No if the client will not connect this system: its act-stage actions stay manual (approx. not reflected in spreadsheet totals; exact on re-import).
A11: ats | B11: Applicant Tracking System | C11: MCP tool → REST/OData connector | D11: Yes | E11: Set to No if the client will not connect this system: its act-stage actions stay manual (approx. not reflected in spreadsheet totals; exact on re-import).
A12: doc-store | B12: Document Management | C12: MCP tool → document pipeline | D12: Yes | E12: Set to No if the client will not connect this system: its act-stage actions stay manual (approx. not reflected in spreadsheet totals; exact on re-import).
... A14: vendor-payroll | B14: Local Payroll Vendors | C14: MCP tool → file/SFTP bridge | D14: Yes | E14: Set to No if the client will not connect this system: its act-stage actions stay manual (approx. not reflected in spreadsheet totals; exact on re-import).

Sheet Intent Mix
A1: Key | B1: Intent | C1: Flow class | D1: Default share | E1: Share override | F1: Note
A2: payslip-copy | B2: Payslip Copy Request | C2: fc1-deterministic | D2: 0.047160635 | F2: OPTIONAL. Fraction of annual volume (0-1). Blank = default mix. Overrides reprice exactly on re-import (not in spreadsheet totals).
A3: salary-certificate | B3: Salary / Employment Certificate | C3: fc1-deterministic | D3: 0.028296381 | F3: OPTIONAL. Fraction of annual volume (0-1). Blank = default mix. Overrides reprice exactly on re-import (not in spreadsheet totals).
A4: tax-form-copy | B4: Tax Form / Statement Copy | C4: fc1-deterministic | D4: 0.023580318 | F4: OPTIONAL. Fraction of annual volume (0-1). Blank = default mix. Overrides reprice exactly on re-import (not in spreadsheet totals).
A5: bank-details-change | B5: Bank Details Change | C5: fc2-policy | D5: 0.023580318 | F5: OPTIONAL. Fraction of annual volume (0-1). Blank = default mix. Overrides reprice exactly on re-import (not in spreadsheet totals).
A6: payroll-discrepancy | B6: Payroll Discrepancy Dispute | C6: fc3-multiagent | D6: 0.020750679 | F6: OPTIONAL. Fraction of annual volume (0-1). Blank = default mix. Overrides reprice exactly on re-import (not in spreadsheet totals).
A7: overpayment-recovery | B7: Overpayment Recovery Setup | C7: fc3-multiagent | D7: 0.0077815048 | F7: OPTIONAL. Fraction of annual volume (0-1). Blank = default mix. Overrides reprice exactly on re-import (not in spreadsheet totals).
A8: off-cycle-payment | B8: Off-Cycle Payment Request | C8: fc3-multiagent | D8: 0.0077815048 | F8: OPTIONAL. Fraction of annual volume (0-1). Blank = default mix. Overrides reprice exactly on re-import (not in spreadsheet totals).
A9: garnishment-query | B9: Garnishment / Wage Attachment Query | C9: fc2-policy | D9: 0.0056592762 | F9: OPTIONAL. Fraction of annual volume (0-1). Blank = default mix. Overrides reprice exactly on re-import (not in spreadsheet totals).
A10: pay-frequency-question | B10: Pay Schedule Question | C10: fc2-policy | D10: 0.018864254 | F10: OPTIONAL. Fraction of annual volume (0-1). Blank = default mix. Overrides reprice exactly on re-import (not in spreadsheet totals).
A11: leave-balance | B11: Leave Balance Inquiry | C11: fc1-deterministic | D11: 0.053055714 | F11: OPTIONAL. Fraction of annual volume (0-1). Blank = default mix. Overrides reprice exactly on re-import (not in spreadsheet totals).
A12: leave-request | B12: Leave Request Submission | C12: fc1-deterministic | D12: 0.042444572 | F12: OPTIONAL. Fraction of annual volume (0-1). Blank = default mix. Overrides reprice exactly on re-import (not in spreadsheet totals).
A13: leave-cancellation | B13: Leave Cancellation / Change | C13: fc1-deterministic | D13: 0.021222286 | F13: OPTIONAL. Fraction of annual volume (0-1). Blank = default mix. Overrides reprice exactly on re-import (not in spreadsheet totals).
... A61: policy-exception-request | B61: Policy Exception Request | C61: fc4-frontier | D61: 0.0038907524 | F61: OPTIONAL. Fraction of annual volume (0-1). Blank = default mix. Overrides reprice exactly on re-import (not in spreadsheet totals).

Sheet Results
A1: Result (annual, directional) | B1: USD | C1: How it is computed
A2: AI consumption | B2: =SUM('Flow Classes'!Q2:Q5) | C2: Per-flow-class AI unit rates x volume, scaled by isolation tier and localization.
A3: Infrastructure | B3: =SUM('Flow Classes'!R2:R5) | C3: Per-flow-class infra unit rates x volume, scaled like AI.
A4: Other run cost | B4: =SUM('Flow Classes'!S2:S5)+6000*Inputs!$C$5 | C4: Other per-txn cost + knowledge maintenance ($6000/country/yr).
A5: Human (HITL + fallback) | B5: =SUM('Flow Classes'!T2:T5) | C5: Sampled review minutes on contained txns + full as-is handling on uncontained fallbacks.
A6: Platform build (amortized) | B6: =SUM('Flow Classes'!U2:U5) | C6: Flow-class build cost amortized over expected volume, scaled by landscape maturity.
A7: Client onboarding (annualized) | B7: =(40000+12000*Inputs!$C$4+8000*Inputs!$C$5)/IF(Inputs!$C$14="",3,Inputs!$C$14) | C7: $40000 base + $12000/system + $8000/country, over the contract term.
A8: TOTAL COST | B8: =B2+B3+B4+B5+B6+B7 | C8: Sum of all cost lines above.
A9: Benefit (time eliminated + dollarized) | B9: =SUM('Flow Classes'!V2:V5) | C9: Handling minutes eliminated on contained txns at the as-is rate + dollarized step benefits.
A10: NET ANNUAL VALUE | B10: =B9-B8 | C10: Benefit minus total cost. Directional — upload this file to the app for the exact engine number.
